{
  "region": "NYIS",
  "hub": "N.Y.C.",
  "iso": "NYISO",
  "fetched_at": "2026-07-23T00:09:33.867336Z",
  "days_back": 14,
  "records": 4363,
  "hourly_avg_price": [
    {
      "hour": 0,
      "price": 46.33
    },
    {
      "hour": 1,
      "price": 43.71
    },
    {
      "hour": 2,
      "price": 40.59
    },
    {
      "hour": 3,
      "price": 38.09
    },
    {
      "hour": 4,
      "price": 37.36
    },
    {
      "hour": 5,
      "price": 40.53
    },
    {
      "hour": 6,
      "price": 43.62
    },
    {
      "hour": 7,
      "price": 44.82
    },
    {
      "hour": 8,
      "price": 45.8
    },
    {
      "hour": 9,
      "price": 47.11
    },
    {
      "hour": 10,
      "price": 50.13
    },
    {
      "hour": 11,
      "price": 51.1
    },
    {
      "hour": 12,
      "price": 58.24
    },
    {
      "hour": 13,
      "price": 57.96
    },
    {
      "hour": 14,
      "price": 62.92
    },
    {
      "hour": 15,
      "price": 72.08
    },
    {
      "hour": 16,
      "price": 77.97
    },
    {
      "hour": 17,
      "price": 119.74
    },
    {
      "hour": 18,
      "price": 78.0
    },
    {
      "hour": 19,
      "price": 118.72
    },
    {
      "hour": 20,
      "price": 69.57
    },
    {
      "hour": 21,
      "price": 59.93
    },
    {
      "hour": 22,
      "price": 56.16
    },
    {
      "hour": 23,
      "price": 49.05
    }
  ]
}